delay_srt/__init__.py
delay_srt/__main__.py
delay_srt/delay_srt.py
delay_srt/time.py
delay_srt-0.2.0.dist-info/LICENSE
delay_srt-0.2.0.dist-info/METADATA
delay_srt-0.2.0.dist-info/WHEEL
delay_srt-0.2.0.dist-info/top_level.txt
delay_srt-0.2.0.dist-info/RECORD
