Metadata-Version: 2.2
Name: delay_srt
Version: 0.2.0
Summary: Delays the subtitles in a SubRip (.srt) file.
Home-page: https://github.com/lewskii/delay_srt
Author: lewski
Keywords: delay subtitles subrip srt
Classifier: Development Status :: 4 - Beta
Classifier: Environment :: Console
Classifier: Intended Audience :: End Users/Desktop
Classifier: License :: OSI Approved :: GNU General Public License v3 or later (GPLv3+)
Classifier: Natural Language :: English
Classifier: Programming Language :: Python :: 3
Classifier: Programming Language :: Python :: 3.11
Classifier: Topic :: Utilities
License-File: LICENSE
Dynamic: author
Dynamic: classifier
Dynamic: description
Dynamic: description-content-type
Dynamic: home-page
Dynamic: keywords
Dynamic: summary
